phyaat/ICA_methods.py
phyaat/ProcessingLib.py
phyaat/__init__.py
phyaat/artifact_correction.py
phyaat/dataset.py
phyaat/utils.py
phyaat-0.0.3.dist-info/LICENSE
phyaat-0.0.3.dist-info/METADATA
phyaat-0.0.3.dist-info/WHEEL
phyaat-0.0.3.dist-info/top_level.txt
phyaat-0.0.3.dist-info/RECORD
