Metadata-Version: 2.1
Name: phyaat
Version: 0.0.3
Summary: PhyAAt: Physiology of Auditory Attention
Home-page: https://phyaat.github.io
Author: Nikesh Bajaj
Author-email: bajaj.nikkey@gmail.com
License: MIT
Project-URL: Documentation, https://phyaat.readthedocs.io/
Project-URL: Say Thanks!, https://github.com/Nikeshbajaj
Project-URL: Source, https://phyaat.github.io
Project-URL: Tracker, https://github.com/Nikeshbajaj/phyaat/issues
Keywords: phyaat auditory-attention attention eeg physiological-signals physiology predictive-analysis artifact EEG EDA Biomedical-signals Electroencephalogram Galvanic-Skin-Response GSR photoplethysmogram PPG
Classifier: Programming Language :: Python :: 3
Classifier: Programming Language :: Python :: 3.5
Classifier: Programming Language :: Python :: 3.6
Classifier: Programming Language :: Python :: 3.7
Classifier: License :: OSI Approved :: MIT License
Classifier: Natural Language :: English
Classifier: Operating System :: OS Independent
Classifier: Development Status :: 5 - Production/Stable
Classifier: Topic :: Scientific/Engineering :: Artificial Intelligence
Classifier: Topic :: Scientific/Engineering :: Information Analysis
Classifier: Topic :: Software Development :: Libraries :: Python Modules
Classifier: Topic :: Multimedia
Classifier: Topic :: Multimedia :: Sound/Audio :: Analysis
Classifier: Topic :: Multimedia :: Sound/Audio :: Speech
Classifier: Topic :: Scientific/Engineering :: Image Processing
Classifier: Topic :: Scientific/Engineering :: Visualization
License-File: LICENSE
Requires-Dist: numpy
Requires-Dist: scipy
Requires-Dist: matplotlib
Requires-Dist: spkit
